mc_toolbox/__init__.py
mc_toolbox/cache.py
mc_toolbox/download.py
mc_toolbox/download_manager.py
mc_toolbox/download_manager_legacy.py
mc_toolbox/exception.py
mc_toolbox/futures.py
mc_toolbox/java.py
mc_toolbox/launch.py
mc_toolbox/natives.json
mc_toolbox/source.py
mc_toolbox/utils.py
mc_toolbox/resources/__init__.py
mc_toolbox-0.3.dist-info/METADATA
mc_toolbox-0.3.dist-info/WHEEL
mc_toolbox-0.3.dist-info/licenses/LICENSE.md
mc_toolbox-0.3.dist-info/RECORD
