Metadata-Version: 2.4
Name: mc_toolbox
Version: 0.3
Summary: This is a Python library that provides downloading and launching of Minecraft.
Project-URL: Source, https://github.com/fdym/mc_toolbox
Project-URL: Bug Tracker, https://github.com/fdym/mc_toolbox/issues
Author: fdym
License-Expression: GPL-2.0-only
License-File: LICENSE.md
Classifier: Development Status :: 4 - Beta
Classifier: Operating System :: OS Independent
Classifier: Programming Language :: Python :: 3
Classifier: Programming Language :: Python :: 3.8
Classifier: Programming Language :: Python :: 3.9
Classifier: Programming Language :: Python :: 3.10
Classifier: Programming Language :: Python :: 3.11
Classifier: Programming Language :: Python :: 3.12
Classifier: Programming Language :: Python :: 3.13
Requires-Python: >=3.8
Requires-Dist: pony
Requires-Dist: pysocks
Requires-Dist: requests
